Assignment 3/Q3/Control.v
`timescale 1ns/1ps

module control(clk,reset,subtract,swap,select,loadx,loady,xgy,xg0,a,b,c2);
output reg subtract,swap,select,loadx,loady,a,b,c2;
input clk,xgy,xg0,reset;
reg c7;

initial begin
    subtract = 0;
    swap = 0;
    select = 1;
    loadx = 1;
    loady = 1;
    a = 0;
    b = 0;
    c2 = 1;
end

always @(posedge clk) begin
 c7 = b;
 b = (a & b) | ((~xg0) & (b)) | ((~xgy) & (~b));
 a = (~xg0) | xgy | c7;
 subtract = a & (~b);
 swap = (~a) & b;
 select = (~a) & (~b);
 loadx = (~a) | (~b);
 loady = (~a);
c2 = ~c2;
end
endmodule

Assignment 3/Q3/Data.v
`timescale 1ns/1ps

module data(X,Y,Z,clk,reset,subtract,swap,select,loadx,loady,xgy,xg0,c2,a,b,XR,YR,ZR,temp);
input clk,reset,c2,a,b,subtract,swap,select,loadx,loady;
input [4:0] X,Y;
output reg xgy,xg0;
output reg [4:0] XR,YR,ZR,Z,temp;

always @(c2) begin
if(a == 1 && b == 1) begin
    Z =ZR;
    #20;
    $finish;
end
if (select == 1) begin
    if(loadx == 1) XR = X;
    if(loady == 1) YR = Y;
end
if (swap == 1) begin
    temp = YR;
    YR = XR;
    XR = temp;
end
if (subtract == 1) XR = XR - YR;
if (XR > 0) begin
    xg0 = 1;
end else begin
    xg0 = 0;
end
if (XR >= YR) begin
    xgy = 1;
end else begin
    xgy = 0;
end
ZR = YR;
end
endmodule

Assignment 3/Q3/GCD.v
`include "Data.v"
`include "Control.v"
`timescale 1ns/1ps

module gcd();
reg clk,reset;
reg [4:0] X,Y;
wire subtract,swap,select,loadx,loady,a,b,c;
wire [4:0] XR,YR,ZR,temp,Z;
initial begin
    $dumpfile("gcd.vcd");
    $dumpvars(0,gcd);
    clk = 0;
    X = 29; Y = 17;
end

always #5 clk = ~clk;

data u1(X,Y,Z,clk,reset,subtract,swap,select,loadx,loady,xgy,xg0,c2,a,b,XR,YR,ZR,temp);
control u2(clk,reset,subtract,swap,select,loadx,loady,xgy,xg0,a,b,c2);

endmodule

Assignment 3/Q3/gcd.vcd
$date
	Sat Apr  3 23:38:45 2021
$end
$version
	Icarus Verilog
$end
$timescale
	1ps
$end
$scope module gcd $end
$var wire 1 ! xgy $end
$var wire 1 " xg0 $end
$var wire 5 # temp [4:0] $end
$var wire 1 $ swap $end
$var wire 1 % subtract $end
$var wire 1 & select $end
$var wire 1 ' loady $end
$var wire 1 ( loadx $end
$var wire 1 ) c2 $end
$var wire 1 * b $end
$var wire 1 + a $end
$var wire 5 , ZR [4:0] $end
$var wire 5 - Z [4:0] $end
$var wire 5 . YR [4:0] $end
$var wire 5 / XR [4:0] $end
$var reg 5 0 X [4:0] $end
$var reg 5 1 Y [4:0] $end
$var reg 1 2 clk $end
$var reg 1 3 reset $end
$scope module u1 $end
$var wire 5 4 X [4:0] $end
$var wire 5 5 Y [4:0] $end
$var wire 1 2 clk $end
$var wire 1 3 reset $end
$var wire 1 $ swap $end
$var wire 1 % subtract $end
$var wire 1 & select $end
$var wire 1 ' loady $end
$var wire 1 ( loadx $end
$var wire 1 ) c2 $end
$var wire 1 * b $end
$var wire 1 + a $end
$var reg 5 6 XR [4:0] $end
$var reg 5 7 YR [4:0] $end
$var reg 5 8 Z [4:0] $end
$var reg 5 9 ZR [4:0] $end
$var reg 5 : temp [4:0] $end
$var reg 1 " xg0 $end
$var reg 1 ! xgy $end
$upscope $end
$scope module u2 $end
$var wire 1 2 clk $end
$var wire 1 3 reset $end
$var wire 1 " xg0 $end
$var wire 1 ! xgy $end
$var reg 1 + a $end
$var reg 1 * b $end
$var reg 1 ) c2 $end
$var reg 1 ; c7 $end
$var reg 1 ( loadx $end
$var reg 1 ' loady $end
$var reg 1 & select $end
$var reg 1 % subtract $end
$var reg 1 $ swap $end
$upscope $end
$upscope $end
$enddefinitions $end
#0
$dumpvars
x;
bx :
b10001 9
bx 8
b10001 7
b11101 6
b10001 5
b11101 4
x3
02
b10001 1
b11101 0
b11101 /
b10001 .
bx -
b10001 ,
0+
0*
1)
1(
1'
1&
0%
0$
bx #
1"
1!
$end
#5000
0!
b1100 /
b1100 6
0)
0'
0&
1%
1+
0;
12
#10000
02
#15000
b1100 ,
b1100 9
1!
b10001 /
b10001 6
b1100 .
b1100 7
b10001 #
b10001 :
1)
1'
1$
0%
0+
1*
12
#20000
02
#25000
0!
b101 /
b101 6
0)
0'
0$
1%
1+
0*
1;
12
#30000
02
#35000
b101 ,
b101 9
1!
b1100 /
b1100 6
b101 .
b101 7
b1100 #
b1100 :
1)
1'
1$
0%
0+
1*
0;
12
#40000
02
#45000
b111 /
b111 6
0)
0'
0$
1%
1+
0*
1;
12
#50000
02
#55000
0!
b10 /
b10 6
1)
0;
12
#60000
02
#65000
b10 ,
b10 9
1!
b101 /
b101 6
b10 .
b10 7
b101 #
b101 :
0)
1'
1$
0%
0+
1*
12
#70000
02
#75000
b11 /
b11 6
1)
0'
0$
1%
1+
0*
1;
12
#80000
02
#85000
0!
b1 /
b1 6
0)
0;
12
#90000
02
#95000
b1 ,
b1 9
1!
b10 /
b10 6
b1 .
b1 7
b10 #
b10 :
1)
1'
1$
0%
0+
1*
12
#100000
02
#105000
b1 /
b1 6
0)
0'
0$
1%
1+
0*
1;
12
#110000
02
#115000
0!
0"
b0 /
b0 6
1)
0;
12
#120000
02
#125000
b1 -
b1 8
0)
0(
0%
1*
12
#130000
02
#135000
1)
1;
12
#140000
02
#145000
0)
12
